{
    "type": "wms",
    "title": "Brennstoffeinsatz bedeutender Heiz- und Kraftwerke 2004 (Umweltatlas)",
    "thumb": "http://fbinter.stadt-berlin.de/fb_daten/vorschau/umweltatlas/karten/kvor_08_02_2heizwerk2004.jpg",
    "link": "http://fbinter.stadt-berlin.de/fb/index.jsp?loginkey=showMap&mapId=k08_02_02heizwerk2004@senstadt",
    "description": {
        "link": "?id=k08_02_02heizwerk2004@senstadt&type=WMS",
        "kurzbeschreibung": "Die Karte verdeutlicht die auch im Kraftwerksbereich in den letzten Jahren vorgenommenen Angleichungen beim Energieträgereinsatz\nin der Stadt. Das \"Rückrat\" des Energieträgereinsatzes in den Berliner Kraftwerken stellen Steinkohle und Erdgas.",
        "koordinatensysteme": "EPSG:3068",
        "ausdehnung": "EPSG:3068: 850, -150, 50350, 40750",
        "ebenen": "Brennstoffeinsatz bedeutender Heiz- und Kraftwerke 2004\nHintergrund 1:5.000\nTexte",
        "nutzungsbedingungen": "Für die Verwendung der Daten gelten folgende Nutzungsbestimmungen: http://www.stadtentwicklung.berlin.de/geoinformation/download/nutzIII.pdf.\nDer Quellenvermerk, der gemäß §2 der o.g. Nutzungsbestimmungen zu verwenden ist, lautet \"Umweltatlas Berlin / [Titel des Datensatzes]\".",
        "zugriffsbeschränkungen": "keine",
        "beschreibung": "Die Karte verdeutlicht die auch im Kraftwerksbereich in den letzten Jahren vorgenommenen Angleichungen beim Energieträgereinsatz\nin der Stadt. Das \"Rückrat\" des Energieträgereinsatzes in den Berliner Kraftwerken stellen Steinkohle und Erdgas."
    },
    "anbieter": {
        "adress": "Senatsverwaltung für Stadtentwicklung und Umwelt Berlin\nBerlin\nFehrbelliner Platz 1, 10707 Berlin\n",
        "contact": {
            "telefon": "+49-30-90139-5257",
            "fax": "+49-30-90139-5251",
            "email": "fisbroker@senstadtum.berlin.de"
        }
    },
    "technology": {
        "standard": [
            "WMS"
        ],
        "version": [
            "1.0.0",
            "1.1.0",
            "1.1.1",
            "1.3.0"
        ],
        "operationen": [
            "GetCapabilities",
            "GetMap",
            "GetFeatureInfo"
        ],
        "grafikformate": [
            "image/jpeg",
            "image/png"
        ],
        "rechneradresse": [
            "http://fbinter.stadt-berlin.de/fb/wms/senstadt/k08_02_02heizwerk2004"
        ],
        "legend": {
            "width": 450,
            "height": 777,
            "format": "image/gif",
            "url": "http://fbinter.stadt-berlin.de/fb_daten/legenden/umweltatlas/leg_heizwerk2004.gif"
        },
        "layers": [
            {
                "name": "0",
                "title": "Brennstoffeinsatz bedeutender Heiz- und Kraftwerke 2004",
                "abstract": "",
                "gdi_de": "d72e6ef1-d3de-3576-9594-c4e48d1694aa",
                "metadata": "http://fbinter.stadt-berlin.de/fb/csw?REQUEST=GetRecordById&SERVICE=CSW&VERSION=2.0.2&ID=0ddb61a7-0980-30e5-9f5b-3708871ecf84&ELEMENTSETNAME=FULL",
                "style": {
                    "name": "gdi_default",
                    "title": "Standard GDI Style"
                },
                "legend": {
                    "width": 300,
                    "height": 300,
                    "url": "http://fbinter.stadt-berlin.de/fb/wms/legend/senstadt/k08_02_02heizwerk2004?layerID=0",
                    "format": "image/png"
                },
                "scalehint": {
                    "min": 25,
                    "max": 105
                },
                "keywords": [
                    "Karten",
                    "Geodaten",
                    "Berlin",
                    "Heizkraftwerke",
                    "Heizwerke",
                    "Heizenergie",
                    "Wohnraumbeheizung",
                    "Fernwärme",
                    "Gas",
                    "Kohle",
                    "Heizöl",
                    "Emissionen"
                ],
                "srs": [
                    {
                        "name": "EPSG:3068",
                        "boundingbox": {
                            "min_latitude": -150,
                            "max_latitude": 40750,
                            "min_longitude": 850,
                            "max_longitude": 50350
                        }
                    },
                    {
                        "name": "EPSG:4326",
                        "boundingbox": {
                            "min_latitude": 52.3246,
                            "max_latitude": 52.6935,
                            "min_longitude": 13.0512,
                            "max_longitude": 13.7785
                        }
                    }
                ]
            },
            {
                "name": "1",
                "title": "Hintergrund 1:5.000",
                "abstract": "",
                "gdi_de": "d72e6ef1-d3de-3576-9594-c4e48d1694aa",
                "metadata": "http://fbinter.stadt-berlin.de/fb/csw?REQUEST=GetRecordById&SERVICE=CSW&VERSION=2.0.2&ID=0ddb61a7-0980-30e5-9f5b-3708871ecf84&ELEMENTSETNAME=FULL",
                "style": {
                    "name": "gdi_default",
                    "title": "Standard GDI Style"
                },
                "legend": {
                    "width": 300,
                    "height": 300,
                    "url": "http://fbinter.stadt-berlin.de/fb/wms/legend/senstadt/k08_02_02heizwerk2004?layerID=1",
                    "format": "image/png"
                },
                "scalehint": {
                    "min": 25,
                    "max": 105
                },
                "keywords": [
                    "Karten",
                    "Geodaten",
                    "Berlin",
                    "Heizkraftwerke",
                    "Heizwerke",
                    "Heizenergie",
                    "Wohnraumbeheizung",
                    "Fernwärme",
                    "Gas",
                    "Kohle",
                    "Heizöl",
                    "Emissionen"
                ],
                "srs": [
                    {
                        "name": "EPSG:3068",
                        "boundingbox": {
                            "min_latitude": -150,
                            "max_latitude": 40750,
                            "min_longitude": 850,
                            "max_longitude": 50350
                        }
                    },
                    {
                        "name": "EPSG:4326",
                        "boundingbox": {
                            "min_latitude": 52.3246,
                            "max_latitude": 52.6935,
                            "min_longitude": 13.0512,
                            "max_longitude": 13.7785
                        }
                    }
                ]
            },
            {
                "name": "2",
                "title": "Texte",
                "abstract": "Die Karte verdeutlicht die auch im Kraftwerksbereich in den letzten Jahren vorgenommenen Angleichungen beim\nEnergieträgereinsatz in der Stadt. Das \"Rückrat\" des Energieträgereinsatzes in den Berliner Kraftwerken stellen Steinkohle und Erdgas.",
                "gdi_de": "d72e6ef1-d3de-3576-9594-c4e48d1694aa",
                "metadata": "http://fbinter.stadt-berlin.de/fb/csw?REQUEST=GetRecordById&SERVICE=CSW&VERSION=2.0.2&ID=0ddb61a7-0980-30e5-9f5b-3708871ecf84&ELEMENTSETNAME=FULL",
                "style": {
                    "name": "gdi_default",
                    "title": "Standard GDI Style"
                },
                "legend": {
                    "width": 300,
                    "height": 300,
                    "url": "http://fbinter.stadt-berlin.de/fb/wms/legend/senstadt/k08_02_02heizwerk2004?layerID=2",
                    "format": "image/png"
                },
                "scalehint": {
                    "min": 25,
                    "max": 105
                },
                "keywords": [
                    "Karten",
                    "Geodaten",
                    "Berlin",
                    "Heizkraftwerke",
                    "Heizwerke",
                    "Heizenergie",
                    "Wohnraumbeheizung",
                    "Fernwärme",
                    "Gas",
                    "Kohle",
                    "Heizöl",
                    "Emissionen"
                ],
                "srs": [
                    {
                        "name": "EPSG:3068",
                        "boundingbox": {
                            "min_latitude": -150,
                            "max_latitude": 40750,
                            "min_longitude": 850,
                            "max_longitude": 50350
                        }
                    },
                    {
                        "name": "EPSG:4326",
                        "boundingbox": {
                            "min_latitude": 52.3246,
                            "max_latitude": 52.6935,
                            "min_longitude": 13.0512,
                            "max_longitude": 13.7785
                        }
                    }
                ]
            }
        ]
    },
    "category": "Umweltatlas",
    "keywords": [
        "Utility and governmental services",
        "Energie",
        "Karten",
        "Geodaten",
        "Berlin",
        "Heizkraftwerke",
        "Heizwerke",
        "Heizenergie",
        "Wohnraumbeheizung",
        "Fernwärme",
        "Gas",
        "Kohle",
        "Heizöl",
        "Emissionen"
    ]
}